sundial/__init__.py
sundial/fields.py
sundial/forms.py
sundial/middleware.py
sundial/utils.py
sundial/zones.py
django_sundial-1.1.1.dist-info/LICENSE
django_sundial-1.1.1.dist-info/METADATA
django_sundial-1.1.1.dist-info/WHEEL
django_sundial-1.1.1.dist-info/top_level.txt
django_sundial-1.1.1.dist-info/RECORD
